{
  "timestamp": "2025-08-07T14:19:07.559Z",
  "totalIssuesFixed": 156,
  "filesModified": 47,
  "modifiedFiles": [
    "multi-account-display.tsx",
    "natural-language-input.tsx",
    "client-modal.tsx",
    "ai-assistant.tsx",
    "banking-connection-card.tsx",
    "financial-cards.tsx",
    "quick-actions.tsx",
    "receipt-upload.tsx",
    "recent-transactions.tsx",
    "estimate-modal.tsx",
    "invoice-modal.tsx",
    "invoice-preview-button.tsx",
    "invoice-preview.tsx",
    "sidebar.tsx",
    "topbar.tsx",
    "receipt-match-suggestions.tsx",
    "receipt-upload.tsx",
    "receipt-viewer.tsx",
    "financial-reports.tsx",
    "transaction-modal.tsx",
    "add-transaction-form.tsx",
    "bulk-actions.tsx",
    "bulk-categorize-button.tsx",
    "double-entry-status.tsx",
    "quick-add-transaction.tsx",
    "transaction-filters.tsx",
    "transaction-review-queue.tsx",
    "carousel.tsx",
    "error-boundary.tsx",
    "pagination.tsx",
    "sidebar.tsx",
    "ai-assistant.tsx",
    "banking.tsx",
    "chart-of-accounts.tsx",
    "clients.tsx",
    "estimates.tsx",
    "invoices.tsx",
    "login.tsx",
    "real-time-reports.tsx",
    "receipts.tsx",
    "register.tsx",
    "reports.tsx",
    "reports_broken.tsx",
    "settings.tsx",
    "subscribe.tsx",
    "transactions-wave-inspired.tsx",
    "transactions.tsx"
  ],
  "summary": {
    "message": "Successfully fixed 156 UI issues across 47 files",
    "status": "completed"
  }
}